slush/__init__.py
slush/app.py
slush/exception.py
slush/server.py
slush/boilerplate/main.py
slush/boilerplate/run.py
slush/cli/__init__.py
slush/cli/run.py
slush/const/__init__.py
slush/const/request.py
slush/core/__init__.py
slush/core/exception.py
slush/core/request.py
slush/core/response.py
slush/core/routing.py
slush/meta/__init__.py
slush/meta/singleton.py
slush/settings/__init__.py
slush/settings/config.py
slush/utils/__init__.py
slush/utils/files.py
slush-0.1.3.dist-info/licenses/LICENSE
slush-0.1.3.dist-info/METADATA
slush-0.1.3.dist-info/WHEEL
slush-0.1.3.dist-info/entry_points.txt
slush-0.1.3.dist-info/top_level.txt
slush-0.1.3.dist-info/RECORD
