Metadata-Version: 2.4
Name: slush
Version: 0.1.3
Summary: A lightweight Python web framework.
Author-email: Hasan Faraz Khan <farazkhan138@gmail.com>
License: BSD-3-Clause
Project-URL: Homepage, https://github.com/farazkhanfk7/slush
Project-URL: Documentation, https://github.com/farazkhanfk7/slush
Project-URL: Source, https://github.com/farazkhanfk7/slush
Keywords: web framework,python,wsgi,slush,backend,api
Requires-Python: >=3.7
License-File: LICENSE
Requires-Dist: gunicorn==23.0.0
Requires-Dist: packaging==25.0
Requires-Dist: watchdog==6.0.0
Requires-Dist: click==8.2.1
Dynamic: license-file
